  {"stars":{"1":{"count":42,"percent":3},"2":{"count":32,"percent":2},"3":{"count":64,"percent":5},"4":{"count":204,"percent":17},"5":{"count":917,"percent":73}},"rating_average":4.5,"reviews_count":1259,"review_photo":{"total":255,"total_photo":441},"data":[{"id":2550277,"title":"\u0110\u00e3 nh\u1eadn h\u00e0ng. Giao nhanh h\u01a1n d\u1ef1 ki\u1ebfn","content":"Nh\u1eadn h\u00e0ng nh\u01b0ng k r\u00f5 l\u00e0 t\u1ea1i sao chu\u1ed9t \u0111\u00e3 b\u1ecb khui kh\u1ecfi h\u1ed9p \u0111\u1ef1ng? C\u00f3 ten c\u1ee7a DGW nh\u01b0ng ten l\u1ea1i d\u00e1n ngo\u00e0i v\u1ecf h\u1ed9p \u0111\u1ef1ng. Chu\u1ed9t \u0111\u00e3 b\u1ecb b\u00f3c kh\u1ecfi h\u1ed9p \u0111\u1ef1ng c\u1ee7a nh\u00e0 s\u1ea3n xu\u1ea5t n\u00ean k bi\u1ebft c\u00f3 ph\u1ea3i chu\u1ed9t ch\u00ednh h\u00e3ng k? \u0110\u1ec1 ngh\u1ecb \u0111\u01a1n v\u1ecb b\u00e1n h\u00e0ng gi\u1ea3i th\u00edch \u0111\u1ec3 kh\u00e1ch h\u00e0ng c\u00f3 c\u00e1i nh\u00ecn kh\u00e1ch quan v\u00e0 tin t\u01b0\u1edfng h\u01a1n Tiki trading! T\u00f4i l\u00e0 kh\u00e1ch th\u01b0\u1eddng xuy\u00ean mua h\u00e0ng tr\u00ean Tiki nh\u01b0ng l\u1ea7n n\u00e0y t\u00f4i nh\u1eadn h\u00e0ng th\u1ea5y kh\u00f4ng y\u00ean t\u00e2m c\u00f3 ph\u1ea3i l\u00e0 s\u1ea3n ph\u1ea9m ch\u00ednh h\u00e3ng?","status":"approved","thank_count":25,"score":0.030760180000000002,"new_score":0.13851764999999999,"customer_id":9066904,"comment_count":5,"rating":3,"images":[{"id":624065,"full_path":"https:\/\/vcdn.tikicdn.com\/ts\/review\/dc\/47\/7c\/976e2b77a0c5150afb881c267fdaf990.jpg"},{"id":624066,"full_path":"https:\/\/vcdn.tikicdn.com\/ts\/review\/65\/60\/03\/caa6524d42af004d994d6c8e8397d1ac.jpg"},{"id":624067,"full_path":"https:\/\/vcdn.tikicdn.com\/ts\/review\/f0\/2c\/7f\/d4d503f25c8d3c1328c9119840954a65.jpg"},{"id":624068,"full_path":"https:\/\/vcdn.tikicdn.com\/ts\/review\/c8\/e3\/cf\/44f3594371647f7e9efc9e5a50086e1f.jpg"},{"id":624069,"full_path":"https:\/\/vcdn.tikicdn.com\/ts\/review\/c9\/39\/87\/20c02f45c1896275faffb9f956ac3bbc.jpg"}],"thanked":false,"created_at":1571744371,"created_by":{"id":9066904,"name":"Vi\u1ec7t Anh","full_name":"Vi\u1ec7t Anh","region":null,"avatar_url":"\/\/tiki.vn\/assets\/img\/avatar.png","purchased":true,"purchased_at":1571539649},"product_id":299461},{"id":2054210,"title":"Tiki c\u1ea7n ph\u1ea3i kh\u1eafc ph\u1ee5c kh\u00e2u giao h\u00e0ng","content":"tr\u01b0\u1edbc gi\u1edd mua h\u00e0ng \u1edf tiki k \u00edt, r\u1ea5t h\u00e0i l\u00f2ng v\u1ec1 vi\u1ec7c \u0111\u00f3ng g\u00f3i v\u00e0 giao h\u00e0ng c\u1ee7a Tiki,  nh\u01b0ng kho\u1ea3ng 3 \u0111\u01a1n g\u1ea7n nh\u1ea5t th\u00ec xu\u1ea5t hi\u1ec7n t\u00ecnh tr\u1ea1ng k ch\u1ea5p nh\u1eadn \u0111c, l\u1ea7n n\u00e0y m\u00ecnh \u0111\u1eb7t mua chu\u1ed9t logitech n\u00e0y, giao h\u00e0ng \u0111\u00e3 tr\u1ec5 h\u1eb9n m\u1eb7c d\u00f9  m g\u1ecdi nh\u1eafc \u0111\u1ebfn 2 l\u1ea7n.\nkhi giao th\u00ec l\u1ea1i g\u00f3i h\u00e0ng v\u00e0o h\u1ed9p k ph\u00f9 h\u1ee3p k\u00edch th\u01b0\u1edbc khi\u1ebfn g\u00f3i h\u00e0ng l\u1ecfng l\u1ebbo, m\u1ed1p m\u00e9o nh\u00ecn r\u1ea5t kinh kh\u1ee7ng, h\u1ed9p l\u1ea1i c\u00f2n b\u1ecb r\u00e1ch, mua thi\u1ebft b\u1ecb \u0111i\u1ec7n t\u1eed \u0111\u00f3ng g\u00f3i ki\u1ec3u n\u00e0y th\u1eadt s\u1ef1 k ch\u1ea5p nh\u1eadn \u0111c.\nk gi\u00e1n tem b\u1ea3o h\u00e0nh tr\u00ean chu\u1ed9t.\nv\u1ec1 ph\u1ea7n chu\u1ed9t th\u00ec c\u1ea7m \u0111\u1ea7m tay, chu\u1ed9t k \u0111\u00e8n n\u00ean khi\u1ebfn m\u00ecnh r\u1ea5t d\u1ec5 ch\u1ecbu, c\u00f2n ti\u1ebft ki\u1ec7m \u0111c pin","status":"approved","thank_count":8,"score":0.0093906200000000006,"new_score":0.12934636999999999,"customer_id":1183151,"comment_count":0,"rating":3,"images":[{"id":374404,"full_path":"https:\/\/vcdn.tikicdn.com\/ts\/review\/36\/4b\/ca\/1ef3f441ef74ed10d6264047dc6658b1.jpg"},{"id":374405,"full_path":"https:\/\/vcdn.tikicdn.com\/ts\/review\/fa\/0c\/01\/228b578b081ba7152dc7f5361678e83e.jpg"},{"id":374406,"full_path":"https:\/\/vcdn.tikicdn.com\/ts\/review\/ff\/52\/3d\/5bdbb6ad091ef9de1f36d68a8920ad7d.jpg"}],"thanked":false,"created_at":1550559942,"created_by":{"id":1183151,"name":"M\u1ef9 H\u1ea3o","full_name":"M\u1ef9 H\u1ea3o","region":null,"avatar_url":"\/\/tiki.vn\/assets\/img\/avatar.png","purchased":true,"purchased_at":1550083980},"product_id":299461},{"id":2652776,"title":"Chu\u1ed9t b\u1ecb \u0111\u00e3 b\u1ecb b\u00f3c v\u1ecf.","content":"Mua l\u1ea7n th\u1ee9 2 c\u1ee7a shop, nh\u01b0ng c\u1ea3m th\u1ea5y th\u1ea5t v\u1ecdng. L\u1ea7n 1 ch\u01b0a b\u1ecb b\u00f3c v\u1ecf, nh\u01b0ng b\u00ean d\u01b0\u1edbi \u0111\u1ebf con chu\u1ed9t c\u00f3 v\u1ebft x\u01b0\u1edbc (b\u1ecf qua). \u0110\u1ebfn l\u1ea7n n\u00e0y mua t\u1eb7ng th\u1ea7y, gi\u1edd b\u1ecb khui h\u1eb3n ra, con chu\u1ed9t nh\u00ecn kh\u00f4ng x\u1ea7y nhi\u1ec1u nh\u01b0 con chu\u1ed9t tr\u01b0\u1edbc. \u0110\u1ec1 ngh\u1ecb tiki ki\u1ec3m tra, gi\u1edd t\u1eb7ng con chu\u1ed9t nh\u01b0 v\u1ea7y t\u00f4i r\u1ea5t ng\u1ea1i!!!","status":"approved","thank_count":0,"score":38.888888889999997,"new_score":0.12838763,"customer_id":5155272,"comment_count":0,"rating":3,"images":[{"id":666459,"full_path":"https:\/\/vcdn.tikicdn.com\/ts\/review\/4c\/74\/a1\/4a107b413cb7ac743fe73976e9a824db.jpg"},{"id":666460,"full_path":"https:\/\/vcdn.tikicdn.com\/ts\/review\/28\/92\/f7\/091271b8a5a507d7ad91e46122127ffe.jpg"}],"thanked":false,"created_at":1574069136,"created_by":{"id":5155272,"name":"Son Tran","region":null,"avatar_url":"\/\/tiki.vn\/assets\/img\/avatar.png","purchased":true,"purchased_at":1573279043},"product_id":299461},{"id":2477786,"title":"Giao h\u00e0ng nhanh, nh\u01b0ng...","content":"Giao h\u00e0ng nhanh, trong 1h \u0111\u00e3 c\u00f3 h\u00e0ng. Nh\u01b0ng khi ki\u1ec3m h\u00e0ng th\u00ec s\u1ea3n ph\u1ea9m \u0111\u00e3 b\u1ecb m\u1edf t\u1eeb tr\u01b0\u1edbc, \u0111\u1ebf chu\u1ed9t c\u00f3 d\u1ea5u hi\u1ec7u b\u1ecb x\u01b0\u1edbc v\u00e0 t\u00ecnh tr\u1ea1ng th\u00ec ko \u0111\u01b0\u1ee3c m\u1edbi ho\u00e0n to\u00e0n. Nh\u01b0ng test s\u1ea3n ph\u1ea9m d\u00f9ng v\u1eabn \u1ed5n v\u00e0 \u00eam n\u00ean m\u00ecnh v\u1eabn nh\u1eadn h\u00e0ng. N\u00f3i chung l\u00e0 th\u1ea5y ko tho\u1ea3i m\u00e1i cho l\u1eafm.","status":"approved","thank_count":0,"score":0.50213675000000002,"new_score":0.12710131999999999,"customer_id":1686543,"comment_count":1,"rating":3,"images":[{"id":584504,"full_path":"https:\/\/vcdn.tikicdn.com\/ts\/review\/ec\/96\/62\/68463e6490bd1ecdc199d5efd2bc65ad.jpg"},{"id":584505,"full_path":"https:\/\/vcdn.tikicdn.com\/ts\/review\/13\/23\/4a\/d342b4051718d3fb13d0adc71ea6f54d.jpg"}],"thanked":false,"created_at":1569464067,"created_by":{"id":1686543,"name":"Clair De Lune","region":null,"avatar_url":"\/\/tiki.vn\/assets\/img\/avatar.png","purchased":true,"purchased_at":1569458602},"product_id":299461},{"id":2097090,"title":"S\u1ea3n ph\u1ea9m chu\u1ed9t Logitech M331 Silent Plus","content":"S\u1ea3n ph\u1ea9m kh\u00f4ng d\u00e1n tem , Khi g\u1eb7p s\u1ef1 c\u1ed1 c\u1ea7n b\u1ea3o h\u00e0nh th\u00ec l\u00e0m sao \u0111\u00e2y .C\u1ea7n s\u1ef1 h\u1ed7 tr\u1ee3 t\u1eeb Tiki (v\u00ec tr\u01b0\u1eddng h\u1ee3p c\u00f3 th\u1ec3 m\u00ecnh s\u1ebd g\u1eedi b\u1ea3o h\u00e0nh b\u00ean Logitech h\u1ecd kh\u00f4ng h\u1ed7 tr\u1ee3 sp kh\u00f4ng c\u00f3 tem)","status":"approved","thank_count":0,"score":0.035917230000000001,"new_score":0.12385204,"customer_id":10243482,"comment_count":1,"rating":3,"images":[{"id":391203,"full_path":"https:\/\/vcdn.tikicdn.com\/ts\/review\/61\/a1\/e3\/fadfdd0864eb12b7036f0edb49faa09f.jpg"},{"id":391204,"full_path":"https:\/\/vcdn.tikicdn.com\/ts\/review\/5e\/f5\/43\/6e74c7bc738af5755b4ed65587780407.jpg"},{"id":391205,"full_path":"https:\/\/vcdn.tikicdn.com\/ts\/review\/44\/8d\/eb\/5491b2e6f539149b345a20caaa511744.jpg"},{"id":391206,"full_path":"https:\/\/vcdn.tikicdn.com\/ts\/review\/99\/13\/8f\/572e45772bb43423112babccdb837902.jpg"},{"id":391207,"full_path":"https:\/\/vcdn.tikicdn.com\/ts\/review\/60\/b1\/62\/3cc9a8cc3c7153f9a1c50990f3604724.jpg"}],"thanked":false,"created_at":1552899362,"created_by":{"id":10243482,"name":"HIEP nguyen","region":null,"avatar_url":"\/\/tiki.vn\/assets\/img\/avatar.png","purchased":true,"purchased_at":1552619584},"product_id":299461},{"id":2932203,"title":"Con l\u0103n chu\u1ed9t kh\u00e1 c\u1ed9m","content":"T\u1ed5ng th\u1ec3 chu\u1ed9t c\u1ea7m kh\u00e1 tho\u1ea3i m\u00e1i, ph\u1ea7n chu\u1ed9t tr\u00e1i v\u00e0 chu\u1ed9t ph\u1ea3i kh\u00e1 \u00eam, kh\u00f4ng ph\u00e1t ra \u00e2m thanh khi \u1ea5n. Nh\u01b0ng ph\u1ea7n con l\u0103n chu\u1ed9t kh\u00e1 c\u1ed9m, t\u1ea1o c\u1ea3m gi\u00e1c h\u01a1i c\u1ed9m, kh\u00f4ng tho\u1ea3i m\u00e1i khi d\u00f9ng, ki\u1ec3u nh\u01b0 b\u1ecb ch\u00eanh v\u00eanh. \nV\u1edbi gi\u00e1 ti\u1ec1n 289k b\u1ecf ra \u0111\u1ec3 mua chu\u1ed9t th\u00ec m\u00ednh kh\u00f4ng h\u00e0i l\u00f2ng l\u1eafm.","status":"approved","thank_count":0,"score":18.518518520000001,"new_score":0.12307397,"customer_id":2090329,"comment_count":0,"rating":3,"images":[],"thanked":false,"created_at":1580568416,"created_by":{"id":2090329,"name":"T\u1ed1ng Nga","full_name":"T\u1ed1ng Nga","region":null,"avatar_url":"\/\/tiki.vn\/assets\/img\/avatar.png","purchased":true,"purchased_at":1580225035},"product_id":299461},{"id":1382998,"title":"Chu\u1ed9t x\u00e0i t\u1ea1m \u1ed5n tr\u00ean Win","content":"L\u00fac giao h\u00e0ng th\u00ec m\u00ecnh th\u1ea5y ph\u00edm chu\u1ed9t ph\u1ea3i b\u1ecb v\u00eanh, ph\u1ea3i d\u00f9ng tay nh\u1ea5n m\u1ea1nh xu\u1ed1ng k\u00eau c\u00e1i t\u1ea1ch :(. Chu\u1ed9t \u00eam ch\u1ea1y t\u1ed1t tr\u00ean windows 10, nh\u01b0ng h\u01a1i lag tr\u00ean macpro 2017. Kh\u00f4ng bi\u1ebft do dpi th\u1ea5p hay sao (1000), n\u00ean th\u00f4i d\u00f9ng l\u00e0m chu\u1ed9t tr\u00ean Cty v\u1eady, ki\u1ebfm con kh\u00e1c cho macbook.","status":"approved","thank_count":0,"score":0.0069500300000000003,"new_score":0.12058357,"customer_id":575087,"comment_count":0,"rating":3,"images":[{"id":145058,"full_path":"https:\/\/vcdn.tikicdn.com\/ts\/review\/20\/c7\/67\/7d768eaee2b51ffa231644feef97bc81.jpg"},{"id":145062,"full_path":"https:\/\/vcdn.tikicdn.com\/ts\/review\/10\/80\/c1\/171106ad09f121a179df846fd93d9bc5.jpg"}],"thanked":false,"created_at":1523842622,"created_by":{"id":575087,"name":"L\u01b0\u01a1ng Ho\u00e0ng Kh\u1ea3i","region":null,"avatar_url":"\/\/tiki.vn\/assets\/img\/avatar.png","purchased":true,"purchased_at":1519277117},"seller":{"id":1,"name":"Tiki Trading","logo":"https:\/\/vcdn.tikicdn.com\/ts\/seller\/ef\/54\/5a\/ef545a8af0f0385f706be0595f932f89.png"},"product_id":299461},{"id":2852672,"title":"ha\u0300ng nguy\u00ean seal nh\u01b0ng bi\u0323 tr\u00e2\u0300y x\u01b0\u01a1\u0301c kha\u0301 nhi\u00ea\u0300u","content":"sau khi \u0111o\u0323c nhi\u00ea\u0300u ba\u0300i nh\u00e2\u0323n xe\u0301t khi cu\u0309a ca\u0301c kha\u0301ch ha\u0300ng trc thi\u0300 mi\u0300nh cu\u0303ng \u0111\u0103\u0323t 1 em v\u00ea\u0300 s\u01b0\u0309 du\u0323ng. Va\u0300 \u0111u\u0301ng la\u0300 chu\u00f4\u0323t tr\u00e2\u0300y r\u00e2\u0301t nhi\u00ea\u0300u m\u0103\u0323c du\u0300 nguy\u00ean seal. kha\u0301 kho\u0301 hi\u00ea\u0309u ch\u00f4\u0309 \u0111o\u0301 th\u00f4i ch\u01b0\u0301 mo\u0323i ch\u01b0\u0301c n\u0103ng v\u00e2\u0303n \u00f4\u0309n","status":"approved","thank_count":0,"score":3.7037037000000002,"new_score":0.11956546999999999,"customer_id":6038843,"comment_count":0,"rating":3,"images":[{"id":751999,"full_path":"https:\/\/vcdn.tikicdn.com\/ts\/review\/23\/6f\/1f\/4500056f2e2c6679e5adeaffaab91bda.jpg"}],"thanked":false,"created_at":1578594028,"created_by":{"id":6038843,"name":"nguy\u1ec5n tr\u1ecdng ph\u00fac","full_name":"nguy\u1ec5n tr\u1ecdng ph\u00fac","region":null,"avatar_url":"\/\/tiki.vn\/assets\/img\/avatar.png","purchased":true,"purchased_at":1578367873},"product_id":299461},{"id":1138034,"title":"S\u1ea3n ph\u1ea9m d\u00f9ng \u0111\u01b0\u1ee3c","content":"Chu\u1ed9t kh\u00e1 nh\u1ea1y, kh\u00f4ng nghe ti\u1ebfng click. Nh\u01b0ng kh\u00e1 b\u1ef1c b\u1ed9i v\u00ec Tiki giao s\u1ea3n ph\u1ea9m \u0111\u00e3 b\u1ecb khui s\u1eb5n (kh\u00f4ng bi\u1ebft c\u00f3 ph\u1ea3i \u0111\u1ec3 ki\u1ec3m tra hay l\u00e0 s\u1ea3n ph\u1ea9m ai \u0111\u00f3 tr\u1ea3 l\u1ea1i v\u00e0 Tiki giao qua m\u00ecnh) v\u00e0 c\u1ee5c pin c\u00f3 s\u1eb5n trong chu\u1ed9t c\u0169ng b\u1ecb c\u1ea1n r\u1ed3i n\u00ean ban \u0111\u1ea7u kh\u00f4ng test chu\u1ed9t \u0111\u01b0\u1ee3c, ph\u1ea3i \u0111i ki\u1ebfm pin kh\u00e1c b\u1ecf v\u00f4. C\u1ea3m th\u1ea5y phi\u1ec1n!","status":"approved","thank_count":1,"score":0.0049304800000000001,"new_score":0.11923449,"customer_id":608522,"comment_count":0,"rating":3,"images":[{"id":86750,"full_path":"https:\/\/vcdn.tikicdn.com\/ts\/review\/27\/8d\/8f\/55334780fc535ccbe5cfde38104ef8f7.jpg"}],"thanked":false,"created_at":1515029344,"created_by":{"id":608522,"name":"Ho\u00e0ng Th\u1ecb Thu Ph\u01b0\u01a1ng","region":null,"avatar_url":"\/\/tiki.vn\/assets\/img\/avatar.png","purchased":true,"purchased_at":1514860984},"seller":{"id":1,"name":"Tiki Trading","logo":"https:\/\/vcdn.tikicdn.com\/ts\/seller\/ef\/54\/5a\/ef545a8af0f0385f706be0595f932f89.png"},"product_id":299461},{"id":1662902,"title":"D\u00f9ng t\u1ea1m \u0111\u01b0\u1ee3c","content":"\u0110\u00e3 mua s\u1ea3n ph\u1ea9m n\u00e0y, m\u1edbi ch\u1ec9 d\u00f9ng dc h\u01a1n 1 ng\u00e0y n\u00ean c\u00f3 1 s\u1ed1 c\u1ea3m nh\u1eadn nh\u01b0 sau:  Ph\u1ea7n b\u1ea5m chu\u1ed9t (2 b\u00ean chu\u1ed9t tr\u00e1i ph\u1ea3i) l\u00e0m b\u1eb1ng nh\u1ef1a b\u00f3ng,  r\u1ea5t d\u1ec5 ph\u00e1t hi\u1ec7n b\u1ea9n. Hai b\u00ean h\u00f4ng ph\u1ee7 cao su, c\u00f3 c\u00e1c r\u00e3nh tam gi\u00e1c t\u1ea1o c\u1ea3m gi\u00e1c \u00eam \u00e1i, nh\u01b0ng s\u1ebd b\u00e1m b\u1ea9n sau n\u00e0y. Chu\u1ed9t tr\u00e1i v\u00e0 ph\u1ea3i h\u00e0nh tr\u00ecnh th\u1ea5p n\u00ean l\u00fac \u0111\u1ea7u b\u1ea5m n\u00f3 ko \u0111\u01b0\u1ee3c t\u1ef1 tin, d\u00f9ng 1 th\u1eddi gian s\u1ebd quen. B\u00ean c\u1ea1nh \u0111\u00f3 2 ph\u00edm b\u1ea5m n\u00e0y kh\u00e1 \u00eam. Tuy nhi\u00ean con tr\u1ecf cu\u1ed9n th\u00ec kh\u00f4ng \u0111\u01b0\u1ee3c \u00eam khi l\u0103n!","status":"approved","thank_count":2,"score":0.0065952800000000002,"new_score":0.11823496,"customer_id":7403080,"comment_count":0,"rating":3,"images":[],"thanked":false,"created_at":1533199637,"created_by":{"id":7403080,"name":"Mai Duy Linh","region":null,"avatar_url":"\/\/tiki.vn\/assets\/img\/avatar.png","purchased":true,"purchased_at":1533004625},"seller":{"id":858,"name":"IT Ch\u00ednh H\u00e3ng","logo":"https:\/\/vcdn.tikicdn.com\/ts\/seller\/8e\/25\/1b\/874fd83ce4e6988bffd8e2c833dd14d5.png"},"product_id":299461},{"id":2053548,"title":"Kh\u00f4ng c\u00f3 tem b\u1ea3o h\u00e0nh","content":"M\u1edbi d\u00f9ng th\u1ea5y c\u0169ng ok. Tuy nhi\u00ean tiki ghi l\u00e0 tem b\u1ea3o h\u00e0nh 12 th\u00e1ng nh\u01b0ng tr\u00ean s\u1ea3n ph\u1ea9m kh\u00f4ng c\u00f3 c\u00e1i tem n\u00e0o, ch\u1ec9 c\u00f3 duy nh\u1ea5t 1tem c\u1ee7a digiworld b\u00ean ngo\u00e0i v\u1ecf. M\u00ecnh t\u01b0\u1edfng c\u00f3 tem b\u00ean d\u01b0\u1edbi tuy nhi\u00ean b\u00f3c ra xem th\u00ec kh\u00f4ng c\u00f3.\nKh\u00f4ng bi\u1ebft n\u1ebfu h\u1ecfng th\u00ec b\u1ea3o h\u00e0nh ki\u1ec3u g\u00ec????","status":"approved","thank_count":0,"score":0.01487569,"new_score":0.11739954,"customer_id":1790632,"comment_count":1,"rating":3,"images":[],"thanked":false,"created_at":1550508324,"created_by":{"id":1790632,"name":"Nguy\u1ec5n M\u1ea1nh H\u00f9ng","region":null,"avatar_url":"\/\/tiki.vn\/assets\/img\/avatar.png","purchased":true,"purchased_at":1550265014},"product_id":299461},{"id":1442866,"title":"C\u0169ng \u0111\u01b0\u1ee3c","content":"M\u00ecnh c\u0169ng th\u1ea5y m\u00e3 tr\u00ean chu\u1ed9t v\u1edbi h\u1ed9p kh\u00f4ng gi\u1ed1ng nhau, h\u1ed9p c\u0169ng \u0111\u00e3 khui nh\u01b0ng m\u00ecnh ngh\u0129 c\u00f3 th\u1ec3 khui \u0111\u1ec3 d\u00e1n tem b\u1ea3o h\u00e0nh, ph\u1ea7n \u0111\u1ec7m d\u01b0\u1edbi chu\u1ed9t c\u0169ng tr\u1ea7y \u00edt, nh\u00ecn k\u0129 m\u1edbi th\u1ea5y, c\u00f2n l\u1ea1i chu\u1ed9t th\u1ea5y m\u1edbi, ko tr\u1ea7y x\u01b0\u1edbc g\u00ec h\u1ebft. X\u00e0i th\u00ec t\u1ed1t, chu\u1ed9t nh\u1ea1y, b\u1ea5m \u00eam, ko nghe ti\u1ebfng, d\u00ed s\u00e1t tai th\u00ec nghe ti\u1ebfng nh\u1ecf l\u1eafm :)))","status":"approved","thank_count":1,"score":0.0052691400000000003,"new_score":0.11737117,"customer_id":6963359,"comment_count":0,"rating":3,"images":[],"thanked":false,"created_at":1525792991,"created_by":{"id":6963359,"name":"H\u1ea1t D\u01b0a","region":null,"avatar_url":"\/\/tiki.vn\/assets\/img\/avatar.png","purchased":true,"purchased_at":1524145694},"seller":{"id":1,"name":"Tiki Trading","logo":"https:\/\/vcdn.tikicdn.com\/ts\/seller\/ef\/54\/5a\/ef545a8af0f0385f706be0595f932f89.png"},"product_id":299461},{"id":1512282,"title":"B\u00ecnh th\u01b0\u1eddng","content":"C\u1ea3m gi\u00e1c qu\u00e1 b\u00ecnh th\u01b0\u1eddng v\u1edbi s\u1ed1 ti\u1ec1n \u0111\u00e3 b\u1ecf ra, kh\u00f4ng nh\u01b0 m\u00ecnh k\u1ef3 v\u1ecdng. Con l\u0103n kh\u00f4ng \u0111\u01b0\u1ee3c m\u01b0\u1ee3t, chu\u1ed9t c\u0169ng b\u00ecnh th\u01b0\u1eddng n\u1ed1t, l\u00fac tr\u01b0\u1edbc m\u00ecnh c\u00f3 mua chu\u1ed9t gi\u00e1 100k nh\u01b0ng c\u1ea3m gi\u00e1c nh\u1ea1y h\u01a1n nhi\u1ec1u. \u0110\u00f3ng g\u00f3i th\u00ec c\u1ea9n th\u1eadn, \u0111i\u1ec1u n\u00e0y kh\u00f4ng c\u00f3 g\u00ec \u0111\u1ec3 n\u00f3i, nh\u01b0ng giao h\u00e0ng tr\u1ec5","status":"approved","thank_count":0,"score":0.0055533300000000004,"new_score":0.11723511,"customer_id":570120,"comment_count":0,"rating":3,"images":[],"thanked":false,"created_at":1528118454,"created_by":{"id":570120,"name":"\u00c2u \u00c1i Linh","region":null,"avatar_url":"\/\/tiki.vn\/assets\/img\/avatar.png","purchased":true,"purchased_at":1527837882},"seller":{"id":858,"name":"IT Ch\u00ednh H\u00e3ng","logo":"https:\/\/vcdn.tikicdn.com\/ts\/seller\/8e\/25\/1b\/874fd83ce4e6988bffd8e2c833dd14d5.png"},"product_id":299461},{"id":2391057,"title":"Trinh - 0937 241 517","content":"hnay em m\u1edbi nh\u1eadn \u0111\u01b0\u1ee3c h\u00e0ng, chu\u1ed9t n\u00e0y l\u00fac x\u00e0i kh\u00f4ng s\u00e1ng \u0111\u00e8n ph\u00eda d\u01b0\u1edbi h\u1ea3 shop? hay l\u00e0 b\u1ecb h\u1ecfng ph\u1ea7n n\u00e0y? tr\u1ea3 l\u1eddi gi\u00fap em v\u1edbi\nchu\u1ed9t n\u00e0y ph\u1ea3i x\u00e0i mi\u1ebfng l\u00f3t chu\u1ed9t m\u1edbi x\u00e0i \u00eam \u0111\u01b0\u1ee3c h\u1ea3 shop? v\u00ec con em mua ko \u00eam l\u1eafm","status":"approved","thank_count":0,"score":0.23371648,"new_score":0.11675591,"customer_id":7111445,"comment_count":2,"rating":3,"images":[{"id":530025,"full_path":"https:\/\/vcdn.tikicdn.com\/ts\/review\/ea\/4a\/26\/995f27eb1d194e0a4dba48650d478279.jpg"}],"thanked":false,"created_at":1566193205,"created_by":{"id":7111445,"name":"THI TUYET TRINH DANG","region":null,"avatar_url":"\/\/tiki.vn\/assets\/img\/avatar.png","purchased":true,"purchased_at":1566022592},"product_id":299461},{"id":2089387,"title":"Ch\u1ea5t l\u01b0\u1ee3ng t\u1ed1t, m\u1eabu m\u00e3 \u0111\u1eb9p, d\u00f9ng \u00eam \u00e1i nh\u01b0ng \u0111\u1ec3 chu\u1ed9t xa c\u1ee5c ph\u00e1t t\u1ea7m 1m v\u1eabn b\u1ecb m\u1ea5t s\u00f3ng","content":"M\u1eb7t h\u00e0ng m\u1eabu m\u00e3 \u0111\u1eb9p, d\u00f9ng r\u1ea5t \u00eam \u00e1i, kh\u00f4ng c\u00f3 ti\u1ebfng click kh\u00f3 ch\u1ecbu.\n\nNh\u01b0ng \u0111\u1ec3 chu\u1ed9t xa \u0111\u1ea7u k\u1ebft n\u1ed1i t\u1ea7m 1m l\u00e0 khi d\u00f9ng s\u1ebd c\u00f3 hi\u1ec7n t\u01b0\u1ee3ng th\u1ec9nh tho\u1ea3ng m\u1ea5t k\u1ebft n\u1ed1i v\u00e0 gi\u1eadt gi\u1eadt kh\u00e1 kh\u00f3 ch\u1ecbu. N\u00ean d\u00f9ng cho laptop th\u00ec s\u1ebd t\u1ed1t h\u01a1n l\u00e0 m\u00e1y \u0111\u1ec3 b\u00e0n.","status":"approved","thank_count":0,"score":0.01730164,"new_score":0.11661354,"customer_id":160220,"comment_count":0,"rating":3,"images":[],"thanked":false,"created_at":1552534719,"created_by":{"id":160220,"name":"Nguy\u1ec5n H\u00f9ng D\u01b0\u01a1ng","region":null,"avatar_url":"\/\/tiki.vn\/assets\/img\/avatar.png","purchased":true,"purchased_at":1529030577},"product_id":299461},{"id":1153626,"title":"V\u1ecf h\u1ed9p \u0111\u1ef1ng chu\u1ed9t kh\u00f4ng kh\u1edbp v\u1edbi m\u00e0u s\u1eafc chu\u1ed9t b\u00ean trong.","content":"M\u00ecnh \u0111\u1eb7c mua chu\u1ed9t m\u00e0u \u0111en th\u00ec nh\u1eadn \u0111\u01b0\u1ee3c \u0111\u00fang s\u1ea3n ph\u1ea9m m\u00e0u \u0111en. Tuy nhi\u00ean ki\u1ec3m tra h\u1ed9p \u0111\u1ef1ng c\u1ee7a chu\u1ed9t th\u00ec l\u1ea1i ghi m\u00e0u \u0111\u1ecf.\nChu\u1ed9t th\u1ef1c t\u1ebf s\u1eed d\u1ee5ng th\u00ec kh\u00e1 \u00eam, tuy nhi\u00ean c\u1ea3m gi\u00e1c \u1ea5n b\u1ecb gi\u1ea3m nhi\u1ec1u so v\u1edbi chu\u1ed9t b\u00ecnh th\u01b0\u1eddng, kh\u00f4ng \u0111\u01b0\u1ee3c s\u00e2u l\u1eafm. N\u00fat cu\u1ed9n khi cu\u1ed9n l\u00ean xu\u1ed1ng v\u1eabn c\u00f2n g\u00e2y \u1ed3n nh\u01b0ng \u0111\u1ee1 h\u01a1n chu\u1ed9t b\u00ecnh th\u01b0\u1eddng. C\u00f2n l\u1ea1i \u1ed5n!","status":"approved","thank_count":1,"score":0.0041628500000000001,"new_score":0.11629365,"customer_id":5089159,"comment_count":0,"rating":3,"images":[],"thanked":false,"created_at":1515589507,"created_by":{"id":5089159,"name":"Nguy\u1ec5n Qu\u1ed1c Th\u1ecbnh","region":null,"avatar_url":"\/\/tiki.vn\/assets\/img\/avatar.png","purchased":true,"purchased_at":1514781154},"seller":{"id":1,"name":"Tiki Trading","logo":"https:\/\/vcdn.tikicdn.com\/ts\/seller\/ef\/54\/5a\/ef545a8af0f0385f706be0595f932f89.png"},"product_id":299461},{"id":2854853,"title":"D\u00d9NG C\u0168NG T\u1ea0M","content":"Mua mua con m\u00e0u \u0111en n\u00e0y tr\u00ean Tiki c\u00e1ch \u0111\u00e2y 5 th\u00e1ng, sau b\u1ecb h\u1ecfng ph\u00edm ch\u1ea5m chu\u1ed9t tr\u00e1i, do ko c\u00f2n phi\u1ebfu b\u1ea3o h\u00e0nh n\u00ean mua m\u1edbi, nh\u01b0ng chu\u1ed9t l\u1ea7n n\u00e0y con l\u0103n ko m\u01b0\u1ee3t nh\u01b0 l\u1ea7n \u0111\u1ea7u, hy v\u1ecdng l\u00e0 \u0111\u1eebng qu\u00e1 nhanh h\u01b0 nh\u01b0 con l\u1ea7n \u0111\u1ea7u","status":"approved","thank_count":0,"score":18.518518520000001,"new_score":0.11527012,"customer_id":1288362,"comment_count":0,"rating":3,"images":[],"thanked":false,"created_at":1578637989,"created_by":{"id":1288362,"name":"Thu Thanh","full_name":"Thu Thanh","region":null,"avatar_url":"\/\/tiki.vn\/assets\/img\/avatar.png","purchased":true,"purchased_at":1561909831},"product_id":299461},{"id":740229,"title":"V\u1eabn x\u00e0i ko t\u1ed1t tr\u00ean MacBook Pro","content":"Tr\u01b0\u1edbc m\u00ecnh x\u00e0i con B175 t\u01b0\u1edfng n\u00f3 c\u00f9i n\u00ean mua con n\u00e0y. Cu\u1ed1i c\u00f9ng th\u00ec nh\u00ecn chung chu\u1ed9t d\u01b0\u1edbi 300k x\u00e0i MacBook Pro s\u1ebd hay b\u1ecb ch\u1ea1y qua \u0111i\u1ec3m m\u00ecnh mu\u1ed1n 1 t\u1eb9o.\r\n\r\n\u0110\u1ed5i l\u1ea1i h\u00e0i l\u00f2ng v\u1ec1 ki\u1ec3u d\u00e1ng, m\u00e0u s\u1eafc, n\u00fat b\u1ea5m \u0111\u00fang silent v\u00e0 n\u00fat cu\u1ed9n chu\u1ed9t ko tr\u01a1n. C\u1ea7m s\u01b0\u1edbng tay. N\u00ean x\u00e0i b\u00e0n di chu\u1ed9t \u0111\u1ec3 nh\u1ea1y h\u01a1n.","status":"approved","thank_count":0,"score":0.0031385499999999999,"new_score":0.11460708,"customer_id":1624785,"comment_count":0,"rating":3,"images":[],"thanked":false,"created_at":1500391668,"created_by":{"id":1624785,"name":"Nguy\u1ec5n Thu\u1ef5 H\u1ed3ng Mai","region":null,"avatar_url":"\/\/tiki.vn\/assets\/img\/avatar.png","purchased":true,"purchased_at":1500093886},"seller":{"id":1,"name":"Tiki Trading","logo":"https:\/\/vcdn.tikicdn.com\/ts\/seller\/ef\/54\/5a\/ef545a8af0f0385f706be0595f932f89.png"},"product_id":299461},{"id":2040965,"title":"chu\u1ed9t ngon \u0111\u1ea5y","content":"chu\u1ed9t ngon, l\u01b0\u1edbt nh\u1ea1y, b\u1ea5m \u00eam, tr\u1ecdng l\u01b0\u1ee3ng v\u1eeba ph\u1ea3i. con n\u00e0y ch\u1eafc ch\u1ec9 h\u1ee3p v\u1edbi laptop, c\u1eafm v\u00e0o m\u00e1y c\u00e2y ch\u1ec9 k\u1ebft n\u1ed1i t\u1ed1t trong kho\u1ea3ng c\u00e1ch 40cm, ra xa ch\u00fat hay c\u00f3 v\u1eadt c\u1ea3n th\u00ec ch\u1ecbu","status":"approved","thank_count":0,"score":0.019110019999999998,"new_score":0.11368644,"customer_id":7468887,"comment_count":0,"rating":3,"images":[{"id":369474,"full_path":"https:\/\/vcdn.tikicdn.com\/ts\/review\/db\/8a\/03\/640a1c207441b46312b7aedcb66ef532.jpg"},{"id":369475,"full_path":"https:\/\/vcdn.tikicdn.com\/ts\/review\/00\/5d\/05\/10e98bb5e02b6db04dd5bee13b5278a7.jpg"}],"thanked":false,"created_at":1549437271,"created_by":{"id":7468887,"name":"M\u1ea1nh Giang","region":null,"avatar_url":"https:\/\/s120.avatar.talk.zdn.vn\/7\/3\/3\/b\/12\/120\/17e6d49a04c8c1314aa45c887ae0f88f.jpg","purchased":true,"purchased_at":1549416573},"product_id":299461},{"id":3232883,"title":"Giao h\u00e0ng kh\u00f4ng \u0111\u00fang v\u1edbi ch\u1ee7ng lo\u1ea1i \u0111\u1eb7t h\u00e0ng M331","content":"\u0110\u01a1n h\u00e0ng Logitech M331 Silent Plus, nh\u01b0ng h\u00e0ng giao l\u1ea1i l\u00e0 Logitech M331 Silent, nh\u01b0 h\u00ecnh \u0111\u00ednh k\u00e8m. N\u00f3i chung h\u00e0ng d\u00f9ng th\u00ec ok, nh\u01b0ng kh\u00f4ng \u01b0ng b\u1edfi l\u00fd do giao kh\u00f4ng \u0111\u00fang khi \u0111\u1eb7t h\u00e0ng.","status":"approved","thank_count":0,"score":33.333333330000002,"new_score":0.11283681,"customer_id":16845940,"comment_count":0,"rating":3,"images":[{"id":903550,"full_path":"https:\/\/vcdn.tikicdn.com\/ts\/review\/9d\/17\/77\/76574d192160d801172146d03806a89d.jpg"}],"thanked":false,"created_at":1584951181,"created_by":{"id":16845940,"name":"Nguy\u1ec5n V\u0129nh An","full_name":"Nguy\u1ec5n V\u0129nh An","region":null,"avatar_url":"\/\/tiki.vn\/assets\/img\/avatar.png","purchased":true,"purchased_at":1584598363},"product_id":299461},{"id":2065496,"title":"GIao h\u00e0ng Ch\u1eadm","content":"S\u1ea3n ph\u1ea9m m\u1edbi d\u00f9ng OK, chu\u1ed9t \u00eam, d\u00f9ng l\u00e2u m\u1edbi bi\u1ebft b\u1ec1n hay kh\u00f4ng. \u0110i\u1ec3m tr\u1eeb l\u00e0 Tiki giao h\u00e0ng l\u00e2u, b\u00e1o giao h\u00e0ng tr\u1ec5 h\u1eb9n t\u1edbi 2 l\u1ea7n. G\u1ea7n n\u1eeda th\u00e1ng m\u00ecnh m\u1edbi nh\u1eadn \u0111\u01b0\u1ee3c h\u00e0ng. Mong Tiki c\u1ea3i thi\u1ec7n v\u1ea5n \u0111\u1ec1 n\u00e0y.","status":"approved","thank_count":0,"score":0.015638550000000001,"new_score":0.11116972,"customer_id":1469957,"comment_count":1,"rating":3,"images":[],"thanked":false,"created_at":1551172847,"created_by":{"id":1469957,"name":"Ph\u1ea1m Xu\u00e2n Tr\u01b0\u1eddng","region":null,"avatar_url":"\/\/tiki.vn\/assets\/img\/avatar.png","purchased":true,"purchased_at":1550401148},"product_id":299461},{"id":2325578,"title":"Abc","content":"Chu\u1ed9t m\u1edbi mua th\u00ec s\u00e0i th\u1ea5y ok. Th\u1ea5y pin \u0111i theo chu\u1ed9t s\u00e0i \u0111c t\u1ea7m 2 3 tu\u1ea7n. R\u1ed3i s\u00e0i \u0111c t\u1ea7m 2 th\u00e1ng c\u00f3 d\u1ea5u hi\u1ec7u gi\u1eadt lag m\u1eb7c d\u00f9 m\u1edbi \u0111\u1ea7u t\u01b0\u1edfng h\u1ebft pin nh\u01b0ng sau khi thay pin th\u00ec v\u1eabn c\u00f2n gi\u1eadt lag","status":"approved","thank_count":0,"score":0.37285607999999998,"new_score":0.11068587000000001,"customer_id":6060963,"comment_count":0,"rating":3,"images":[],"thanked":false,"created_at":1563636058,"created_by":{"id":6060963,"name":"Nguy\u1ec5n Huy","region":null,"avatar_url":"\/\/tiki.vn\/assets\/img\/avatar.png","purchased":true,"purchased_at":1557330819},"product_id":299461},{"id":2152710,"title":"Ho\u00e0n thi\u1ec7n ch\u01b0a t\u1ed1t","content":"TIKI cho h\u1ecfi chu\u1ed9t b\u1ecb 1 v\u1ea1ch g\u1edd l\u00ean do ho\u00e0n thi\u1ec7n c\u1ee7a chu\u1ed9t nh\u01b0 v\u1eady hay do chu\u1ed9t c\u1ee7a t\u00f4i b\u1ecb l\u1ed7i ?\n\u1ea2nh tr\u00ean web c\u1ee7a TIKI th\u00ec kh\u00f4ng th\u1ea5y v\u1ea1ch n\u00e0y.","status":"approved","thank_count":2,"score":0.032896250000000002,"new_score":0.11017942999999999,"customer_id":1876602,"comment_count":1,"rating":3,"images":[{"id":414803,"full_path":"https:\/\/vcdn.tikicdn.com\/ts\/review\/30\/1d\/bd\/bde716d7970cfac869a919fd73322d2e.jpg"},{"id":414804,"full_path":"https:\/\/vcdn.tikicdn.com\/ts\/review\/6f\/36\/97\/8864f597d74f3393dcb4482052717354.jpg"}],"thanked":false,"created_at":1555400447,"created_by":{"id":1876602,"name":"Huy Ho\u00e0ng","region":null,"avatar_url":"\/\/tiki.vn\/assets\/img\/avatar.png","purchased":true,"purchased_at":1555055855},"product_id":299461},{"id":2985377,"title":"Ch\u1ea5t l\u01b0\u1ee3ng trung b\u00ecnh","content":"H\u00e0ng \u0111\u01b0\u1ee3c \u0111\u00f3ng g\u00f3i c\u1ea9n th\u1eadn. Ch\u1ea5t l\u01b0\u1ee3ng chu\u1ed9t trung b\u00ecnh v\u00ec \u0111\u1ec3 \u0111\u1ea7u usb receiver h\u01a1i xa ch\u00fat l\u00e0 chu\u1ed9t gi\u1eadt gi\u1eadt h\u01a1i kh\u00f3 ch\u1ecbu. Kho\u1ea3ng c\u00e1ch \u0111\u01b0\u1ee3c t\u1ea7m 40cm \u0111\u1ed5 l\u1ea1i th\u00f4i.","status":"approved","thank_count":0,"score":18.518518520000001,"new_score":0.10996943000000001,"customer_id":5708093,"comment_count":0,"rating":3,"images":[],"thanked":false,"created_at":1581472293,"created_by":{"id":5708093,"name":"Tu\u1ea5n B\u00f9i Anh","full_name":"Tu\u1ea5n B\u00f9i Anh","region":null,"avatar_url":"\/\/tiki.vn\/assets\/img\/avatar.png","purchased":true,"purchased_at":1581252039},"product_id":299461},{"id":1420538,"title":"Con l\u0103n h\u01a1i \u1ed3n","content":"Logitech l\u00e0m ch\u1ea5t l\u01b0\u1ee3ng ko \u0111\u1ed3ng \u0111\u1ec1u. Con 331 \u0111\u1ee3t n\u00e0y n\u00e0y mua con l\u0103n x\u00e0i \u1ed3n gh\u00ea, ko \u00eam nh\u01b0 2 con tr\u01b0\u1edbc t\u1eebng mua. C\u00e1i con n\u00e0y ch\u1ea3 hi\u1ec3u sao c\u1ee9 x\u00e0i t\u1ea7m 3-4 th\u00e1ng l\u00e0 con l\u0103n b\u1ecb h\u01b0.","status":"approved","thank_count":1,"score":0.0061870400000000004,"new_score":0.10748784,"customer_id":415014,"comment_count":0,"rating":3,"images":[{"id":155902,"full_path":"https:\/\/vcdn.tikicdn.com\/ts\/review\/a7\/f6\/16\/833d093bd0d5ec732c53a14d8c210ab7.jpg"}],"thanked":false,"created_at":1525003931,"created_by":{"id":415014,"name":"V\u00f5 Nh\u1ea5t T\u00e2m","region":null,"avatar_url":"\/\/tiki.vn\/assets\/img\/avatar.png","purchased":true,"purchased_at":1524809762},"seller":{"id":858,"name":"NPP IT Ch\u00ednh H\u00e3ng","logo":"https:\/\/vcdn.tikicdn.com\/ts\/seller\/57\/df\/eb\/18a5576c2a09a88d0a05af1ab6cd05d8.jpg"},"product_id":299461},{"id":2119808,"title":"T\u1ea1m \u1ed5n","content":"M\u00ecnh mua v\u1ec1 d\u00f9ng \u0111\u01b0\u1ee3c v\u00e0i ng\u00e0y m\u1edbi ph\u00e1t hi\u1ec7n ra l\u00e0 chu\u1ed9t tr\u00e1i b\u1ecb k\u00eanh, nh\u00f4 cao h\u01a1n chu\u1ed9t ph\u1ea3i, c\u0169ng kh\u00f4ng kh\u00f3 ch\u1ecbu l\u1eafm \u0111\u00e2y l\u00e0 l\u1ed7i nh\u1ecf. Kh\u00f4ng bi\u1ebft c\u00f3 \u0111\u1ed5i \u0111\u01b0\u1ee3c kh\u00f4ng?","status":"approved","thank_count":0,"score":0.019619270000000001,"new_score":0.10704647,"customer_id":10068386,"comment_count":1,"rating":3,"images":[],"thanked":false,"created_at":1553793499,"created_by":{"id":10068386,"name":"\u0110\u1ea1t H\u1ed3","region":null,"avatar_url":"https:\/\/graph.facebook.com\/788373368172385\/picture?type=large&return_ssl_resources=1","purchased":true,"purchased_at":1553278501},"product_id":299461},{"id":2214917,"title":"B\u00ecnh th\u01b0\u1eddng","content":"\u01afu: Ch\u1ea5t li\u1ec7u t\u1ed1t, click ch\u1ed1ng \u1ed3n r\u1ea5t t\u1ed1t\nNh\u01b0\u1ee3c: H\u01a1i nh\u1ecf so v\u1edbi ng\u01b0\u1eddi tay to; hai \u0111\u1ea7u ch\u1ed7 ti\u1ebfp x\u00fac con l\u0103n thi\u1ebft k\u1ebf k\u00e9m, l\u00e0m nh\u00f4 \u0111\u00e0u nh\u1ecdn ra n\u00ean r\u1ea5t kh\u00f3 ch\u1ecbu","status":"approved","thank_count":1,"score":0.036649969999999997,"new_score":0.1067337,"customer_id":7247373,"comment_count":0,"rating":3,"images":[],"thanked":false,"created_at":1558581227,"created_by":{"id":7247373,"name":"Cao Hoang Hai","region":null,"avatar_url":"\/\/tiki.vn\/assets\/img\/avatar.png","purchased":true,"purchased_at":1557729803},"product_id":299461},{"id":2768015,"title":"\u0110\u00e8n chu\u1ed9t l\u00fac s\u00e1ng l\u00fac kh\u00f4ng","content":"M\u00ecnh m\u1edbi nh\u1eadn chu\u1ed9t h\u00f4m qua. Ch\u01b0a th\u1ea5y v\u1ea5n \u0111\u1ec1 g\u00ec. Nh\u01b0ng cho m\u00ecnh h\u1ecfi l\u00e0 sao \u0111\u1eebn ph\u00eda tr\u00ean chu\u1ed9t l\u00fac s\u00e1ng l\u00fac kh\u00f4ng nh\u1ec9. C\u00f3 ph\u1ea3i l\u1ed7i kh\u00f4ng?","status":"approved","thank_count":0,"score":1.0790598300000001,"new_score":0.1056038,"customer_id":15017643,"comment_count":1,"rating":3,"images":[],"thanked":false,"created_at":1577063110,"created_by":{"id":15017643,"name":"Vu thi phuong duyen","region":null,"avatar_url":"\/\/tiki.vn\/assets\/img\/avatar.png","purchased":true,"purchased_at":1576894808},"product_id":299461},{"id":3092319,"title":"Chu\u1ed9t silent nh\u01b0ng b\u1ea5m k\u00eau","content":"M\u00ecnh mua 585 590 h t\u1edbi con 331 n\u00e0y. Hai con kia b\u1ea5m k nghe \u0111\u00fang l\u00e0 silent. Con n\u00e0y b\u1ea5m k\u00eau t\u1ea1ch t\u1ea1ch m\u1eb7c d\u00f9 k to","status":"approved","thank_count":0,"score":22.222222219999999,"new_score":0.10454777,"customer_id":7576027,"comment_count":0,"rating":3,"images":[{"id":857440,"full_path":"https:\/\/vcdn.tikicdn.com\/ts\/review\/cc\/af\/9f\/4e349a1fb2e088b92921fc49ecc97f27.jpg"}],"thanked":false,"created_at":1583161142,"created_by":{"id":7576027,"name":"Son Nguyen","full_name":"Son Nguyen","region":null,"avatar_url":"https:\/\/lh4.googleusercontent.com\/-uZaNkWlYS8I\/AAAAAAAAAAI\/AAAAAAAAX8A\/M4Mluvh64WI\/photo.jpg","purchased":true,"purchased_at":1583122693},"product_id":299461},{"id":2393165,"title":"T\u1ea1m \u1ed5n","content":"X\u00e0i t\u1ea1m \u1ed5n, c\u1ea7m \u00eam v\u00e0 ch\u1eafc tay, \u0111\u1ed9 ph\u00e2n gi\u1ea3i 1000 DPI n\u00ean kh\u00f4ng nh\u1ea1y l\u1eafm :) Ho\u1ea1t \u0111\u1ed9ng t\u1ed1t nh\u1ea5t khi k\u00e8m mousepad.","status":"approved","thank_count":1,"score":0.33114395000000002,"new_score":0.10413538999999999,"customer_id":438239,"comment_count":0,"rating":3,"images":[{"id":531291,"full_path":"https:\/\/vcdn.tikicdn.com\/ts\/review\/9d\/b1\/0f\/e811308f913e4d32cf5f2d7b899012a8.jpg"}],"thanked":false,"created_at":1566265827,"created_by":{"id":438239,"name":"Phan V\u0103n \u0110\u1eadm","region":null,"avatar_url":"\/\/tiki.vn\/assets\/img\/avatar.png","purchased":true,"purchased_at":1565582861},"product_id":299461},{"id":2693366,"title":"B\u00ecnh th\u01b0\u1eddng","content":"du\u0300ng ch\u01b0a \u0111c 1 n\u0103m thi\u0300 chu\u00f4\u0323t tra\u0301i co\u0301 d\u00e2\u0301u hi\u00ea\u0323u li\u00ea\u0323t, nh\u01b0 v\u00e2\u0323y co\u0301 \u0111\u01b0\u01a1\u0323c ba\u0309o ha\u0300nh hay ko ? Mi\u0300nh mua nha\u0300 cung c\u00e2\u0301p tikitrading","status":"approved","thank_count":0,"score":27.777777780000001,"new_score":0.10390692,"customer_id":1823533,"comment_count":0,"rating":3,"images":[],"thanked":false,"created_at":1575198768,"created_by":{"id":1823533,"name":"L\u00ea H\u1ed3ng S\u01a1n","region":null,"avatar_url":"\/\/tiki.vn\/assets\/img\/avatar.png","purchased":true,"purchased_at":1547000492},"product_id":299461},{"id":1027754,"title":"B\u00ecnh th\u01b0\u1eddng","content":"khi t\u00f4i d\u00f9ng v\u1edbi thao t\u00e1c nhi\u1ec1u v\u00e0 nhanh th\u00ec c\u1ea3m th\u1ea5y chu\u1ed9t kh\u00f4ng \u0111\u01b0\u1ee3c chu\u1ea9n x\u00e1c. v\u00ed d\u1ee5 nh\u01b0 ch\u01a1i game. T\u00f4i mu\u1ed1n h\u1ecfi l\u00e0 nh\u01b0 v\u1eady c\u00f3 ph\u1ea3i l\u00e0 l\u1ed7i kh\u00f4ng hay chu\u1ed9t quang n\u00e0o c\u0169ng v\u1eady","status":"approved","thank_count":1,"score":0.0039077799999999996,"new_score":0.10350632,"customer_id":6061851,"comment_count":1,"rating":3,"images":[],"thanked":false,"created_at":1511921701,"created_by":{"id":6061851,"name":"Nguy\u1ec5n Xu\u00e2n T\u00f9ng","region":null,"avatar_url":"\/\/tiki.vn\/assets\/img\/avatar.png","purchased":true,"purchased_at":1510571160},"seller":{"id":1,"name":"Tiki Trading","logo":"https:\/\/vcdn.tikicdn.com\/ts\/seller\/ef\/54\/5a\/ef545a8af0f0385f706be0595f932f89.png"},"product_id":299461},{"id":1552698,"title":"S\u1ea3n ph\u1ea9m kh\u00f4ng c\u00f2n nguy\u00ean tem","content":"S\u1ea3n ph\u1ea9m \u0111\u00e3 b\u1ecb m\u1edf ra, kh\u00f4ng c\u00f2n nguy\u00ean tem, \u0111\u01b0\u1ee3c d\u00e1n l\u1ea1i b\u1eb1ng b\u0103ng keo trong. Seal d\u00e1n kh\u00f4ng \u0111\u00fang v\u1ecb tr\u00ed n\u1eafp pin. Ch\u1ea5t l\u01b0\u1ee3ng ok nh\u01b0ng nghi ng\u1edd \u0111\u00e3 qua s\u1eed d\u1ee5ng.","status":"approved","thank_count":1,"score":0.0058917300000000004,"new_score":0.10316369,"customer_id":665847,"comment_count":1,"rating":3,"images":[],"thanked":false,"created_at":1529509956,"created_by":{"id":665847,"name":"Hu\u1ef3nh Th\u1ecb Th\u00f9y Trang","region":null,"avatar_url":"\/\/tiki.vn\/assets\/img\/avatar.png","purchased":true,"purchased_at":1491463276},"seller":{"id":1,"name":"Tiki Trading","logo":"https:\/\/vcdn.tikicdn.com\/ts\/seller\/ef\/54\/5a\/ef545a8af0f0385f706be0595f932f89.png"},"product_id":299461},{"id":3251197,"title":"H\u00e0ng c\u00f3 d\u1ea5u hi\u1ec7u tr\u1ea7u s\u01b0\u1edbt","content":"M\u1edbi mua nh\u01b0ng th\u1ea5y h\u00e0ng \u0111\u00e3 b\u1ecb s\u01b0\u1edbt \u1edf \u0111\u1ebf v\u00e0 2 mi\u1ebfng nh\u1ef1a tr\u00e1i ph\u1ea3i chu\u1ed9t kh\u00f4ng c\u00e2n x\u1ee9ng b\u1ecb l\u1ec7ch","status":"approved","thank_count":0,"score":13.88888889,"new_score":0.10155649,"customer_id":1389871,"comment_count":0,"rating":3,"images":[],"thanked":false,"created_at":1585137537,"created_by":{"id":1389871,"name":"Nh\u00e2n H\u1ed3","full_name":"Nh\u00e2n H\u1ed3","region":null,"avatar_url":"\/\/tiki.vn\/assets\/img\/avatar.png","purchased":true,"purchased_at":1585012119},"product_id":299461},{"id":2012414,"title":"Tem b\u1ea3o h\u00e0nh","content":"m\u00ecnh mua 1 em m\u00e0u xanh.\nh\u00e0ng t\u1ed1t. b\u1ea5m \u00eam.\n\nm\u1ed1i n\u1ed1i ch\u01b0a kh\u1edbp. d\u00e1n tem b\u1ea3o h\u00e0nh qu\u00e1 ngu.","status":"approved","thank_count":1,"score":0.01662775,"new_score":0.10132426999999999,"customer_id":34330,"comment_count":0,"rating":3,"images":[{"id":359126,"full_path":"https:\/\/vcdn.tikicdn.com\/ts\/review\/26\/75\/8d\/13b0fcd01dfe58f1020b6121818d016a.jpg"},{"id":359127,"full_path":"https:\/\/vcdn.tikicdn.com\/ts\/review\/ba\/d4\/74\/dbce6b1152882e9b66c5b4324bfe4ebb.jpg"}],"thanked":false,"created_at":1547128659,"created_by":{"id":34330,"name":"Ng\u00f4 Long Ph\u1ee5ng","region":null,"avatar_url":"\/\/tiki.vn\/assets\/img\/avatar.png","purchased":true,"purchased_at":1546917214},"product_id":299461},{"id":1658578,"title":"li\u1ec7t n\u00fat chu\u1ed9t tr\u00e1i b\u1ea3o h\u00e0nh nh\u01b0 th\u1ebf n\u00e0o?","content":"M\u00ecnh mua h\u00e0ng t\u1eeb 27\/12\/2017, \u0111\u1ebfn h\u00f4m nay b\u1ed7ng d\u01b0ng b\u1ecb li\u1ec7t n\u00fat b\u1ea5m b\u00ean tr\u00e1i, ph\u1ea3i b\u1ea5m m\u1ea1nh m\u1edbi \u0111\u01b0\u1ee3c. V\u1eady m\u00ecnh c\u00f3 \u0111\u01b0\u1ee3c b\u1ea3o h\u00e0nh kh\u00f4ng?","status":"approved","thank_count":0,"score":0.00644197,"new_score":0.10075922,"customer_id":458779,"comment_count":0,"rating":3,"images":[],"thanked":false,"created_at":1533081531,"created_by":{"id":458779,"name":"\u0110inh  Quy\u00ea\u0301t","region":null,"avatar_url":"\/\/tiki.vn\/assets\/img\/avatar.png","purchased":true,"purchased_at":1514358924},"seller":{"id":1,"name":"Tiki Trading","logo":"https:\/\/vcdn.tikicdn.com\/ts\/seller\/ef\/54\/5a\/ef545a8af0f0385f706be0595f932f89.png"},"product_id":299461},{"id":1242274,"title":"B\u00ecnh th\u01b0\u1eddng","content":"H\u00e0ng giao nhanh, chu\u1ed9t nh\u1eadn t\u00edn hi\u1ec7u t\u1ed1t, n\u00fat \u1ea5n \u00eam kh\u00f4ng c\u00f3 ti\u1ebfng clicky.\nCh\u1ec9 c\u00f3 \u0111i\u1ec1u h\u00e0ng ghi l\u00e0 silent plus nh\u01b0ng l\u1ea1i g\u1eedi cho m\u00ecnh b\u1ea3n silent. @@","status":"approved","thank_count":1,"score":0.0045522599999999998,"new_score":0.099933010000000003,"customer_id":2056739,"comment_count":0,"rating":3,"images":[],"thanked":false,"created_at":1519750015,"created_by":{"id":2056739,"name":"Hi\u1ebfu L\u00ea Quang","region":null,"avatar_url":"\/\/tiki.vn\/assets\/img\/avatar.png","purchased":true,"purchased_at":1519406625},"seller":{"id":1,"name":"Tiki Trading","logo":"https:\/\/vcdn.tikicdn.com\/ts\/seller\/ef\/54\/5a\/ef545a8af0f0385f706be0595f932f89.png"},"product_id":299461},{"id":1402878,"title":"ch\u01b0a h\u00e0i l\u00f2ng l\u1eafm","content":"v\u1eeba nh\u1eadn h\u00e0ng nh\u01b0ng bao b\u00ec sp kh\u00f4ng ph\u1ea3i m\u1edbi nguy\u00ean m\u00e0 \u0111\u00e3 b\u1ecb m\u1edf s\u1eb5n. kh\u00f4ng th\u00edch \u0111i\u1ec1u n\u00e0y. ch\u1ea5t l\u01b0\u1ee3ng th\u1ebf n\u00e0o s\u1ebd c\u1eadp nh\u1eadt th\u00eam sau.","status":"approved","thank_count":0,"score":0.0041173599999999996,"new_score":0.099547899999999995,"customer_id":497313,"comment_count":0,"rating":3,"images":[],"thanked":false,"created_at":1524451850,"created_by":{"id":497313,"name":"Nguy\u1ec5n  Tr\u1ecdng","region":null,"avatar_url":"\/\/tiki.vn\/assets\/img\/avatar.png","purchased":true,"purchased_at":1524106957},"product_id":299461},{"id":2732948,"title":"Used","content":"V\u1eeba m\u1edbi nh\u1eadn t\u1ee9c th\u00ec m\u00e0 \u0111\u1ebf gi\u1ed1ng nh\u01b0 c\u00f3 ng\u01b0\u1eddi d\u00f9ng r\u1ed3i. Ch\u00e1n","status":"approved","thank_count":0,"score":22.222222219999999,"new_score":0.099013199999999996,"customer_id":181711,"comment_count":0,"rating":3,"images":[{"id":703488,"full_path":"https:\/\/vcdn.tikicdn.com\/ts\/review\/35\/cb\/25\/5335215d50f25e855b67d33e7d0097e2.jpg"}],"thanked":false,"created_at":1576205138,"created_by":{"id":181711,"name":"H\u1eb1ng Milk","region":null,"avatar_url":"\/\/tiki.vn\/assets\/img\/avatar.png","purchased":true,"purchased_at":1576062372},"product_id":299461},{"id":1365330,"title":"T\u1ea1m \u1ed5n","content":"Chu\u1ed9t d\u00f9ng t\u1ed1t, tuy nhi\u00ean h\u00e0ng nh\u1eadn \u0111\u01b0\u1ee3c b\u1ecb tr\u1ea7n \u1edf \u0111\u1ec3 chu\u1ed9t kh\u00e1 nhi\u1ec1u, nh\u00ecn nghi\u00eang k\u0129 s\u1ebd th\u1ea5y, c\u00f3 v\u1ebb nh\u01b0 h\u00e0ng tr\u1ea3 b\u1ea3oh\u00e0nh","status":"approved","thank_count":0,"score":0.00489778,"new_score":0.098624879999999998,"customer_id":642656,"comment_count":0,"rating":3,"images":[],"thanked":false,"created_at":1523286847,"created_by":{"id":642656,"name":"Nguy\u1ec5n Nh\u1eadt Th\u00e0nh","region":null,"avatar_url":"\/\/tiki.vn\/assets\/img\/avatar.png","purchased":true,"purchased_at":1522330868},"seller":{"id":858,"name":"NPP IT Ch\u00ednh H\u00e3ng","logo":"https:\/\/vcdn.tikicdn.com\/ts\/seller\/57\/df\/eb\/18a5576c2a09a88d0a05af1ab6cd05d8.jpg"},"product_id":299461},{"id":1488962,"title":"B\u00ecnh th\u01b0\u1eddng","content":"Mua v\u1ec1 \u0111ang d\u00f9ng \u0111\u01b0\u1ee3c m\u1ea5y ng\u00e0y th\u1ea5y okay, nh\u01b0ng sao tr\u00ean web l\u00e0 silent plus m\u00e0 tr\u00ean h\u1ed9p kh\u00f4ng c\u00f3 ch\u1eef plus.","status":"approved","thank_count":0,"score":0.0065155100000000004,"new_score":0.098448160000000007,"customer_id":1436540,"comment_count":0,"rating":3,"images":[{"id":175746,"full_path":"https:\/\/vcdn.tikicdn.com\/ts\/review\/da\/7c\/f4\/329bbb241dbc8039e0fb622f4a4a556c.jpg"}],"thanked":false,"created_at":1527295127,"created_by":{"id":1436540,"name":"NGUY\u1ec4N QUANG VINH","region":null,"avatar_url":"\/\/tiki.vn\/assets\/img\/avatar.png","purchased":true,"purchased_at":1526996729},"seller":{"id":858,"name":"IT Ch\u00ednh H\u00e3ng","logo":"https:\/\/vcdn.tikicdn.com\/ts\/seller\/57\/df\/eb\/18a5576c2a09a88d0a05af1ab6cd05d8.jpg"},"product_id":299461},{"id":2213910,"title":"\u0110\u00e8n chu\u1ed9t k s\u00e1ng","content":"Chu\u1ed9t d\u00f9ng ok nh\u01b0ng \u0111\u00e8n k h\u1ec1 s\u00e1ng. H\u00ecnh nh\u01b0 b\u1ecb \u0111\u1ee9t d\u00e2y \u0111\u00e8n hay sao \u0111\u00f3. Tiki ktra l\u1ea1i gi\u00fap m\u00ecnh","status":"approved","thank_count":0,"score":0.03622409,"new_score":0.097645300000000004,"customer_id":6892866,"comment_count":1,"rating":3,"images":[],"thanked":false,"created_at":1558517204,"created_by":{"id":6892866,"name":"Tr\u1ea7n Khanh","region":null,"avatar_url":"\/\/tiki.vn\/assets\/img\/avatar.png","purchased":true,"purchased_at":1558509875},"product_id":299461},{"id":3190056,"title":"B\u00ecnh th\u01b0\u1eddng","content":"N\u00fat b\u1ea5m m\u1ec1m qu\u00e1. C\u1ea3m bi\u1ebfn \u0111\u1ec3 ph\u00eda sau n\u00ean kh\u00f3 di chuy\u1ec3n con tr\u1ecf h\u01a1n.","status":"approved","thank_count":0,"score":6.9444444399999998,"new_score":0.097389630000000005,"customer_id":5485299,"comment_count":0,"rating":3,"images":[],"thanked":false,"created_at":1584504447,"created_by":{"id":5485299,"name":"H\u00e0 \u0110\u1ed7","full_name":"H\u00e0 \u0110\u1ed7","region":null,"avatar_url":"\/\/tiki.vn\/assets\/img\/avatar.png","purchased":true,"purchased_at":1582513959},"product_id":299461},{"id":1658350,"title":"B\u00ecnh th\u01b0\u1eddng","content":"Chu\u1ed9t c\u0169, kh\u00f4ng ph\u1ea3i h\u00e0ng nguy\u00ean seal, nh\u00ecn h\u1ed9p v\u00e0 s\u1ea3n ph\u1ea9m r\u1ea5t lem nhem. Th\u1ea5t v\u1ecdng v\u1edbi h\u00e0ng b\u00e1n b\u1edfi Tiki Trading.","status":"approved","thank_count":0,"score":0.0064345100000000001,"new_score":0.097255999999999995,"customer_id":6738944,"comment_count":0,"rating":3,"images":[],"thanked":false,"created_at":1533051003,"created_by":{"id":6738944,"name":"Anh Linh","region":null,"avatar_url":"\/\/tiki.vn\/assets\/img\/avatar.png","purchased":true,"purchased_at":1532701393},"seller":{"id":1,"name":"Tiki Trading","logo":"https:\/\/vcdn.tikicdn.com\/ts\/seller\/ef\/54\/5a\/ef545a8af0f0385f706be0595f932f89.png"},"product_id":299461},{"id":1931138,"title":"Ch\u01b0a h\u00e0i l\u00f2ng","content":"Ch\u1ea5t l\u01b0\u1ee3ng v\u1ecf c\u1ee7a chu\u1ed9t ch\u01b0a t\u1ed1t, s\u1eed d\u1ee5ng m\u1ed9t th\u1eddi gian b\u1ecb bung nh\u1eefng mi\u1ebfng \u0111\u1ec7m cao su hai b\u00ean ra.","status":"approved","thank_count":1,"score":0.0091789799999999998,"new_score":0.097091430000000006,"customer_id":781675,"comment_count":0,"rating":3,"images":[],"thanked":false,"created_at":1542082908,"created_by":{"id":781675,"name":"Tr\u01b0\u01a1ng Kh\u00e1nh","region":null,"avatar_url":"\/\/tiki.vn\/assets\/img\/avatar.png","purchased":true,"purchased_at":1514275418},"product_id":299461},{"id":2112276,"title":"Kh\u00f4ng h\u00e0i l\u00f2ng","content":"S\u1ea3n ph\u1ea9m \u0111\u00e3 b\u1ecb b\u00f3c, kh\u00f4ng c\u00f2n nguy\u00ean seal. V\u00ec gi\u00e1 tr\u1ecb kh\u00f4ng qu\u00e1 l\u1edbn, v\u1eabn d\u00f9ng ok n\u00ean cho qua","status":"approved","thank_count":2,"score":0.019267820000000001,"new_score":0.096979300000000004,"customer_id":1901232,"comment_count":0,"rating":3,"images":[],"thanked":false,"created_at":1553505292,"created_by":{"id":1901232,"name":"\u0110\u1ed7 Ho\u00e0ng D\u0169ng","region":null,"avatar_url":"\/\/tiki.vn\/assets\/img\/avatar.png","purchased":true,"purchased_at":1553484412},"product_id":299461},{"id":2531479,"title":"T\u1ed1t","content":"Ch\u1ea5t l\u01b0\u1ee3ng t\u1ed1t nh\u01b0ng tiki giao h\u00e0ng qu\u00e1 l\u00e2u m\u1edbi t\u1edbi Ph\u00fa M\u1ef9, V\u0169ng T\u00e0u.","status":"approved","thank_count":0,"score":18.518518520000001,"new_score":0.095997479999999996,"customer_id":8324898,"comment_count":0,"rating":3,"images":[],"thanked":false,"created_at":1571321607,"created_by":{"id":8324898,"name":"Steve Gate","region":null,"avatar_url":"https:\/\/s120.avatar.talk.zdn.vn\/0\/9\/b\/f\/27\/120\/14dbdb01acc0f49c0c219bc69b00ade7.jpg","purchased":true,"purchased_at":1554350381},"product_id":299461},{"id":1699678,"title":"H\u00c0NG C\u0168.","content":"CHU\u1ed8T NH\u1eacN DC \u0110\u00c3 X\u00c0I QUA R\u1ed2I BAO B\u00cc TH\u00cc B\u1eca R\u00c1CH, NH\u00c2N VI\u00caN GIAO H\u00c0NG TH\u00cc KH\u00d4NG CHO TH\u1eec CHU\u1ed8T KHI NH\u1eacN.","status":"approved","thank_count":1,"score":0.0068112499999999996,"new_score":0.095988270000000001,"customer_id":2005662,"comment_count":0,"rating":3,"images":[],"thanked":false,"created_at":1534477437,"created_by":{"id":2005662,"name":"Vic Pham","region":null,"avatar_url":"\/\/tiki.vn\/assets\/img\/avatar.png","purchased":true,"purchased_at":1534393095},"seller":{"id":858,"name":"IT Ch\u00ednh H\u00e3ng","logo":"https:\/\/vcdn.tikicdn.com\/ts\/seller\/8e\/25\/1b\/874fd83ce4e6988bffd8e2c833dd14d5.png"},"product_id":299461},{"id":2050376,"title":"kh\u00f4ng d\u00e1n tem b\u1ea3o h\u00e0nh","content":"m\u1edbi nh\u1eadn h\u00e0ng d\u00f9ng ok nh\u01b0ng t\u1ea1i sao b\u1ea3o h\u00e0nh b\u1eb1ng tem m\u00e0 kh\u00f4ng d\u00e1n tem b\u1ea3o h\u00e0nh????","status":"approved","thank_count":0,"score":0.0088225400000000002,"new_score":0.095178399999999996,"customer_id":2141415,"comment_count":0,"rating":3,"images":[],"thanked":false,"created_at":1550308096,"created_by":{"id":2141415,"name":"Hau Quach","region":null,"avatar_url":"\/\/tiki.vn\/assets\/img\/avatar.png","purchased":true,"purchased_at":1550298044},"product_id":299461},{"id":1852958,"title":"Chu\u1ed9t Kh\u00f4ng D\u00e2y Logitech M331","content":"nh\u1eadn h\u00e0ng v\u1ecf \u0111\u00e3 b\u1ecb b\u00f3c.  ki\u1ec3m tra th\u00ec s\u1ed1 seri tr\u00ean v\u1ecf bao v\u00e0 tr\u00ean chu\u1ed9t kh\u00e1c nhau.","status":"approved","thank_count":1,"score":0.00806078,"new_score":0.094272949999999994,"customer_id":8263288,"comment_count":0,"rating":3,"images":[],"thanked":false,"created_at":1539067139,"created_by":{"id":8263288,"name":"th\u00e2n v\u0103n tu\u1ea5n","region":null,"avatar_url":"\/\/tiki.vn\/assets\/img\/avatar.png","purchased":true,"purchased_at":1538823562},"product_id":299461},{"id":997254,"title":"kh\u00f4ng check serial tr\u00ean trang ch\u1ee7 logitech \u0111\u01b0\u1ee3c!?","content":"kh\u00f4ng check serial tr\u00ean trang ch\u1ee7 logitech \u0111\u01b0\u1ee3c!?\nadmin ki\u1ec3m tra l\u1ea1i th\u00f4ng tin h\u00e0ng gi\u00fap!","status":"approved","thank_count":0,"score":0.0045277599999999996,"new_score":0.09413821,"customer_id":6055504,"comment_count":0,"rating":3,"images":[{"id":60834,"full_path":"https:\/\/vcdn.tikicdn.com\/ts\/review\/3e\/13\/fd\/e4c0caac1450793f0fcbb49482d686a3.jpg"}],"thanked":false,"created_at":1511102864,"created_by":{"id":6055504,"name":"nguy\u1ec5n t\u00f9ng","region":null,"avatar_url":"\/\/tiki.vn\/assets\/img\/avatar.png","purchased":true,"purchased_at":1510474584},"seller":{"id":1,"name":"Tiki Trading","logo":"https:\/\/vcdn.tikicdn.com\/ts\/seller\/ef\/54\/5a\/ef545a8af0f0385f706be0595f932f89.png"},"product_id":299461},{"id":1017382,"title":"t\u1ea1m","content":"Hai b\u00ean click v\u1eabn nghe ti\u1ebfng v\u00e0 kh\u00f4ng th\u1eadt s\u1ef1 tr\u01a1n  tru, con l\u0103n gi\u1eefa th\u00ec ch\u1eafc th\u1ea3m h\u1ecda, c\u1ee9 k\u00eau k\u1ecdt k\u1eb9t.","status":"approved","thank_count":0,"score":0.0038072599999999998,"new_score":0.094090140000000003,"customer_id":303299,"comment_count":0,"rating":3,"images":[],"thanked":false,"created_at":1511594571,"created_by":{"id":303299,"name":"Nguy\u1ec5n Minh V\u0169","region":null,"avatar_url":"\/\/tiki.vn\/assets\/img\/avatar.png","purchased":true,"purchased_at":1510538656},"seller":{"id":1,"name":"Tiki Trading","logo":"https:\/\/vcdn.tikicdn.com\/ts\/seller\/ef\/54\/5a\/ef545a8af0f0385f706be0595f932f89.png"},"product_id":299461},{"id":1321526,"title":"Ch\u01b0a \u0111\u01b0\u1ee3c \u01b0ng \u00fd l\u1eafm","content":"sau m\u1ed9t th\u1eddi gian s\u1eed d\u1ee5ng, ph\u00edm scroll tr\u00ean chu\u1ed9t t\u00f4i th\u1ea5y kh\u00f4ng \u0111\u01b0\u1ee3c nh\u1ea1y v\u00e0 tr\u01a1n tru cho l\u1eafm","status":"approved","thank_count":0,"score":0.0047634000000000001,"new_score":0.093903769999999998,"customer_id":5999945,"comment_count":0,"rating":3,"images":[],"thanked":false,"created_at":1522140040,"created_by":{"id":5999945,"name":"Trung Duong Thanh","region":null,"avatar_url":"\/\/tiki.vn\/assets\/img\/avatar.png","purchased":true,"purchased_at":1520308566},"seller":{"id":858,"name":"NPP IT Ch\u00ednh H\u00e3ng","logo":"https:\/\/vcdn.tikicdn.com\/ts\/seller\/57\/df\/eb\/18a5576c2a09a88d0a05af1ab6cd05d8.jpg"},"product_id":299461},{"id":1561518,"title":"Ch\u01b0a t\u1ed1t l\u1eafm","content":"M\u1eb7t d\u01b0\u1edbi c\u1ee7a chu\u1ed9t kh\u00f4ng b\u1eb1ng ph\u1eb3ng, khi b\u1ea5m chu\u1ed9t b\u1ecb c\u1eadp k\u00eanh n\u00ean h\u01a1i kh\u00f3 ch\u1ecbu","status":"approved","thank_count":1,"score":0.0058995999999999996,"new_score":0.09350398,"customer_id":1985270,"comment_count":0,"rating":3,"images":[],"thanked":false,"created_at":1529891544,"created_by":{"id":1985270,"name":"Mai Thanh D\u01b0\u01a1ng","region":null,"avatar_url":"\/\/tiki.vn\/assets\/img\/avatar.png","purchased":true,"purchased_at":1521075794},"seller":{"id":858,"name":"IT Ch\u00ednh H\u00e3ng","logo":"https:\/\/vcdn.tikicdn.com\/ts\/seller\/8e\/25\/1b\/874fd83ce4e6988bffd8e2c833dd14d5.png"},"product_id":299461},{"id":1935038,"title":"T\u1ea1m \u0111\u01b0\u1ee3c","content":"Chu\u1ed9t oke, nh\u01b0ng h\u01a1i n\u1eb7ng, n\u00fat cu\u1ed9n kh\u00f4ng t\u1ed1t g\u00e2y c\u1ea3m gi\u00e1c r\u1ea5t kh\u00f3 ch\u1ecbu.","status":"approved","thank_count":1,"score":0.0092883800000000006,"new_score":0.093418619999999994,"customer_id":6165238,"comment_count":0,"rating":3,"images":[],"thanked":false,"created_at":1542340449,"created_by":{"id":6165238,"name":"S\u01a1n Nguy\u1ec5n H\u1eefu","region":null,"avatar_url":"\/\/tiki.vn\/assets\/img\/avatar.png","purchased":true,"purchased_at":1540655802},"product_id":299461},{"id":2088393,"title":"click \u00eam","content":"click \u0111\u00fang l\u00e0 \u00eam thi\u1ec7t\nx\u00e0i ko bi\u1ebft th\u01a1i gian th\u1ebf n\u00e0o nh\u01b0ng kh\u00e1 \u1ed5n","status":"approved","thank_count":0,"score":0.017221190000000001,"new_score":0.093307390000000004,"customer_id":11260432,"comment_count":0,"rating":3,"images":[],"thanked":false,"created_at":1552476490,"created_by":{"id":11260432,"name":"Anna Nguyen","region":null,"avatar_url":"https:\/\/lh4.googleusercontent.com\/-wvt4_lOzNmE\/AAAAAAAAAAI\/AAAAAAAABVY\/ifxq2hRSfRU\/photo.jpg","purchased":true,"purchased_at":1552403385},"product_id":299461},{"id":1933981,"title":"nh\u1eadn x\u00e9t","content":"n\u00fat b\u1ea5m m\u01b0\u1ee3t nh\u01b0ng con l\u0103n kh\u00f4ng \u00eam tay, g\u00e2y \u0111au tay v\u00e0 c\u00f3 ti\u1ec1ng \u1ed3n l\u1edbn.","status":"approved","thank_count":0,"score":0.0091479600000000001,"new_score":0.093229549999999994,"customer_id":7497884,"comment_count":0,"rating":3,"images":[],"thanked":false,"created_at":1542270009,"created_by":{"id":7497884,"name":"luong nguyen thanh trang ","region":null,"avatar_url":"\/\/tiki.vn\/assets\/img\/avatar.png","purchased":true,"purchased_at":1541989523},"product_id":299461},{"id":1991489,"title":"B\u1ecb h\u1ecfng r\u1ed3i, b\u1ea3o h\u00e0nh \u1edf \u0111\u00e2u?","content":"B\u1ecb h\u1ecfng r\u1ed3i, b\u1ea3o h\u00e0nh \u1edf \u0111\u00e2u? \nB\u1ecb h\u1ecfng r\u1ed3i, b\u1ea3o h\u00e0nh \u1edf \u0111\u00e2u?","status":"approved","thank_count":0,"score":0.010876190000000001,"new_score":0.092797169999999998,"customer_id":269129,"comment_count":0,"rating":3,"images":[],"thanked":false,"created_at":1545751117,"created_by":{"id":269129,"name":"Nguyen Joseph","region":null,"avatar_url":"\/\/tiki.vn\/assets\/img\/avatar.png","purchased":true,"purchased_at":1543235459},"product_id":299461},{"id":1336814,"title":"chu\u00f4\u0323t","content":"Sa\u0309n ph\u00e2\u0309m \u0111a\u0303 giao l\u00e2\u0300n 2 nh\u01b0ng ma\u0300u s\u0103\u0301c v\u00e2\u0303n ko \u0111u\u0301ng nh\u01b0 hi\u0300nh a\u0309nh m\u00f4 ta\u0309.","status":"approved","thank_count":0,"score":0.0048058399999999996,"new_score":0.091843400000000006,"customer_id":1024956,"comment_count":0,"rating":3,"images":[],"thanked":false,"created_at":1522515275,"created_by":{"id":1024956,"name":"Ph\u1ea1m Minh \u0110\u1ee9c","region":null,"avatar_url":"\/\/tiki.vn\/assets\/img\/avatar.png","purchased":true,"purchased_at":1515135243},"seller":{"id":1,"name":"Tiki Trading","logo":"https:\/\/vcdn.tikicdn.com\/ts\/seller\/ef\/54\/5a\/ef545a8af0f0385f706be0595f932f89.png"},"product_id":299461},{"id":1624138,"title":"B\u00ecnh th\u01b0\u1eddng","content":"c\u1ea3m nh\u1eadn ban \u0111\u1ea7u l\u00e0 d\u00f9ng kh\u00f4ng ngon nh\u01b0 qu\u1ea3ng c\u00e1o s\u1ea3n ph\u1ea9m","status":"approved","thank_count":0,"score":0.0062177500000000002,"new_score":0.090541460000000004,"customer_id":7197826,"comment_count":0,"rating":3,"images":[],"thanked":false,"created_at":1531966425,"created_by":{"id":7197826,"name":"Th\u00e0nh T\u1ea1 V\u0103n","region":null,"avatar_url":"\/\/tiki.vn\/assets\/img\/avatar.png","purchased":true,"purchased_at":1531366823},"seller":{"id":1,"name":"Tiki Trading","logo":"https:\/\/vcdn.tikicdn.com\/ts\/seller\/ef\/54\/5a\/ef545a8af0f0385f706be0595f932f89.png"},"product_id":299461},{"id":1092946,"title":"Ch\u01b0a h\u00e0i l\u00f2ng l\u1eafm","content":"V\u1eabn c\u00f3 ti\u1ebfng \u1ed3n kh\u00e1 kh\u00f3 ch\u1ecbu khi click, nh\u1ea5t l\u00e0 v\u00e0o ban \u0111\u00eam y\u00ean t\u0129nh.","status":"approved","thank_count":0,"score":0.0039679700000000004,"new_score":0.089813329999999997,"customer_id":6189522,"comment_count":0,"rating":3,"images":[],"thanked":false,"created_at":1513708061,"created_by":{"id":6189522,"name":"Nguyen Quang Minh","region":null,"avatar_url":"\/\/tiki.vn\/assets\/img\/avatar.png","purchased":true,"purchased_at":1513091091},"seller":{"id":858,"name":"NPP IT Ch\u00ednh H\u00e3ng","logo":"https:\/\/vcdn.tikicdn.com\/ts\/seller\/57\/df\/eb\/18a5576c2a09a88d0a05af1ab6cd05d8.jpg"},"product_id":299461},{"id":2328421,"title":"C\u1ea3m nh\u1eadn c\u00e1 nh\u00e2n kh\u00f4ng \u0111\u01b0\u1ee3c Good cho l\u1eafm .","content":"C\u1ea3m nh\u1eadn chu\u1ed9t x\u00e0i h\u01a1i t\u1ec7 ( chu\u1ed9t l\u00e2u l\u00e2u b\u1ecb delay , n\u00fat cu\u1ed9n nh\u1ecf x\u00edu  , cu\u1ed9n l\u00e2u d\u1ec5 m\u1ecfi ng\u00f3n tay , chu\u1ed9t nh\u1ecf , c\u1ea7m m\u1ecfi tay  ) bi\u1ebft l\u00e0 gi\u00e1 300k m\u00e0 kh\u00f4ng d\u00e2y th\u00ec kh\u00f4ng th\u1ec3 \u0111\u00f2i h\u1ecfi nhi\u1ec1u nh\u01b0ng c\u00e1 nh\u00e2n \u0111\u00e1nh gi\u00e1 thua con chu\u1ed9t B100 gi\u00e1 60k . \u0110\u00f3 l\u00e0 1 ch\u00fat l\u01b0u \u00fd cho anh em n\u00e0o mu\u1ed1n tr\u1ea3i nghi\u1ec7m kh\u00f4ng d\u00e2y gi\u00e1 r\u1ebb :D","status":"approved","thank_count":0,"score":0,"new_score":0.061302160000000001,"customer_id":1524179,"comment_count":0,"rating":3,"images":[],"thanked":false,"created_at":1563790357,"created_by":{"id":1524179,"name":"D\u01b0\u01a1ng Ho\u00e0i \u0110\u1ee9c","region":null,"avatar_url":"\/\/tiki.vn\/assets\/img\/avatar.png","purchased":false,"purchased_at":null},"product_id":299461},{"id":1243274,"title":"Scroll","content":"Bi cu\u1ed9n c\u1ee7a chu\u1ed9t c\u00f3 v\u1ebb kh\u00f4ng \u0111\u01b0\u1ee3c b\u1ec1n cho l\u1eafm. M\u00ecnh \u0111\u00e3 d\u00f9ng \u0111\u01b0\u1ee3c 6 th\u00e1ng, do v\u1ebd autocad cu\u1ed9n kh\u00e1 nhi\u00eau n\u00ean gi\u1edd b\u00e1nh xe c\u00f3 c\u1ea3m gi\u00e1c l\u1ecfng, kh\u00f4ng c\u00f2n ch\u1eafc nh\u01b0 l\u00fac \u0111\u1ea7u, v\u00e0 \u0111\u00f4i khi l\u0103n kh\u00f4ng nh\u1ea1y nh\u01b0 l\u00fac m\u1edbi mua m\u00e0 c\u00f3 tr\u1ec5 ho\u1eb7c kh\u00f4ng nh\u1eadn. B\u1ea1n n\u00e0o x\u00e0i l\u0103n nhi\u1ec1u n\u00ean c\u00e2n nh\u1eafc","status":"approved","thank_count":0,"score":0,"new_score":0.056656230000000002,"customer_id":236099,"comment_count":0,"rating":3,"images":[],"thanked":false,"created_at":1519796007,"created_by":{"id":236099,"name":"Tr\u1ea7n  Qu\u1ed1c To\u1ea3n","region":null,"avatar_url":"\/\/tiki.vn\/assets\/img\/avatar.png","purchased":false,"purchased_at":null},"product_id":299461},{"id":1978267,"title":"Silent ch\u1ee9 ko ph\u1ea3i Silent Plus","content":"H\u00f4m nay nh\u1eadn chu\u1ed9t m\u00e0u xanh.\nD\u00f9 c\u00f9ng m\u00e3 M331 nh\u01b0ng chu\u1ed9t n\u00e0y l\u00e0 silent ch\u1ee9 ko ph\u1ea3i silent plus.\nChu\u1ed9t c\u00f3 d\u1ea5u hi\u1ec7u b\u1ecb m\u1edf tr\u01b0\u1edbc \u1edf ph\u1ea7n \u0111\u1ea7u.","status":"approved","thank_count":0,"score":0.0026414099999999999,"new_score":0.047922939999999997,"customer_id":887992,"comment_count":0,"rating":3,"images":[{"id":346674,"full_path":"https:\/\/vcdn.tikicdn.com\/ts\/review\/81\/26\/d4\/ae3dfb609c6cac5c84e5160b62bcdc92.jpg"},{"id":346675,"full_path":"https:\/\/vcdn.tikicdn.com\/ts\/review\/cf\/38\/4e\/200e85d9b6bfeeb07c114e8a26d2a4a8.jpg"}],"thanked":false,"created_at":1545048228,"created_by":{"id":887992,"name":"Le Bao Tri","region":null,"avatar_url":"\/\/tiki.vn\/assets\/img\/avatar.png","purchased":true,"purchased_at":1544619463},"product_id":299461}],"paging":{"total":64,"per_page":300,"current_page":1,"last_page":1,"from":1,"to":300},"sort_options":[[{"label":"H\u1eefu \u00edch","value":"score|desc"},{"label":"M\u1edbi nh\u1ea5t","value":"id|desc"},{"label":"C\u00f3 h\u00ecnh \u1ea3nh","value":"has_image"}],[{"label":"T\u1ea5t c\u1ea3 kh\u00e1ch h\u00e0ng","value":"customer|all"},{"label":"Kh\u00e1ch \u0111\u00e3 mua h\u00e0ng","value":"bought"}],[{"label":"T\u1ea5t c\u1ea3 sao","value":"stars|all"},{"label":"5 sao","value":"stars|5"},{"label":"4 sao","value":"stars|4"},{"label":"3 sao","value":"stars|3"},{"label":"2 sao","value":"stars|2"},{"label":"1 sao","value":"stars|1"},{"label":"H\u00e0i l\u00f2ng","value":"stars|4|5"},{"label":"Ch\u01b0a h\u00e0i l\u00f2ng","value":"stars|1|2|3"}]],"exclude_image":false}